src/__init__.py
src/custom_indicators.py
src/utils.py
src/data/__init__.py
src/data/historical.py
src/data/live.py
src/orders/__init__.py
src/orders/kite.py
src/orders/orders.py
sysstra/__init__.py
sysstra/custom_indicators.py
sysstra/utils.py
sysstra/data/__init__.py
sysstra/data/historical.py
sysstra/data/live.py
sysstra/orders/__init__.py
sysstra/orders/backtest.py
sysstra/orders/common.py
sysstra/orders/kite.py
sysstra/orders/live.py
sysstra/orders/orders.py
sysstra/orders/virtual.py
sysstra-0.1.8.dist-info/LICENSE
sysstra-0.1.8.dist-info/METADATA
sysstra-0.1.8.dist-info/WHEEL
sysstra-0.1.8.dist-info/top_level.txt
sysstra-0.1.8.dist-info/RECORD
