Metadata-Version: 2.1
Name: sysstra
Version: 0.1.8
Summary: Official Python Library for Sysstra Algo Trading
Home-page: https://github.com/sysstra/sysstra
Author: Anurag Singh Kushwah
Author-email: anurag@techrefic.com
Classifier: Programming Language :: Python :: 3
Classifier: License :: OSI Approved :: MIT License
Classifier: Operating System :: OS Independent
Requires-Python: >=3.9
License-File: LICENSE
Requires-Dist: requests
Requires-Dist: numpy
Requires-Dist: pandas-ta
Requires-Dist: redis
Requires-Dist: bson
